{
  "id": "nodebb-${type}-${id}",
  "version": "${version}",
  "name": "${name}",
  "description": "${description}",
  "library": "@{ID}.js",
  "staticDirs": {},
  "less": [],
  "languages": "locales",
  "templates": "templates",
  "hooks": [
    {
      "hook": "action:plugin.activate",
      "method": "pluginActivation"
    },
    {
      "hook": "filter:admin.header.build",
      "method": "addAdminNavigation"
    },
    {
      "hook": "action:app.load",
      "method": "init"
    }
  ],
  "nbbpm": {
    "compatibility": "^0.7.0"
  }
}
